q_index_mcp/__init__.py
q_index_mcp/mcp_server.py
q_index_mcp/test_mcp_client.py
q_index_mcp/utils/__init__.py
q_index_mcp/utils/async_utils.py
q_index_mcp/utils/constants.py
q_index_mcp/utils/tvm_client.py
mseep_acme_company_mcp-0.1.1.dist-info/METADATA
mseep_acme_company_mcp-0.1.1.dist-info/WHEEL
mseep_acme_company_mcp-0.1.1.dist-info/top_level.txt
mseep_acme_company_mcp-0.1.1.dist-info/RECORD
