Metadata-Version: 2.4
Name: mseep-acme-company-mcp
Version: 0.1.1
Summary: Acme Company MCP server
Author-email: mseep <support@skydeck.ai>
Requires-Python: >=3.12
Requires-Dist: boto3>=1.38.3
Requires-Dist: mcp[cli]>=1.6.0
Requires-Dist: requests>=2.32.0
Requires-Dist: fastmcp>=2.6.1
Requires-Dist: httpx>=0.28.1
Requires-Dist: python-dotenv>=1.1.0
Requires-Dist: strands-agents>=0.1.6
Requires-Dist: strands-agents-tools>=0.1.4
